LICENSE
suitetalk_connector/__init__.py
suitetalk_connector/netsuite-v2022_1_0.wsdl
suitetalk_connector/netsuite-v2023_1_0.wsdl
suitetalk_connector/restconnector.py
suitetalk_connector/soapadaptor.py
suitetalk_connector/soapconnector.py
suitetalk_connector-0.0.4.dist-info/LICENSE
suitetalk_connector-0.0.4.dist-info/METADATA
suitetalk_connector-0.0.4.dist-info/WHEEL
suitetalk_connector-0.0.4.dist-info/RECORD
