Metadata-Version: 2.1
Name: SuiteTalk-Connector
Version: 0.0.4
Summary: Use to connect NetSuite SuiteTalk SOAP API.
Home-page: https://github.com/ideabosque/suitetalk_connector
License: MIT
Author: Idea Bosque
Author-email: ideabosque@gmail.com
Requires-Python: >=3.6,<4.0
Classifier: Environment :: Web Environment
Classifier: Intended Audience :: Developers
Classifier: License :: OSI Approved :: MIT License
Classifier: Operating System :: OS Independent
Classifier: Programming Language :: Python
Classifier: Programming Language :: Python :: 3
Classifier: Programming Language :: Python :: 3.6
Classifier: Programming Language :: Python :: 3.7
Classifier: Programming Language :: Python :: 3.8
Classifier: Programming Language :: Python :: 3.9
Classifier: Programming Language :: Python :: 3.10
Classifier: Programming Language :: Python :: 3.11
Classifier: Programming Language :: Python :: 3.12
Classifier: Topic :: Internet :: WWW/HTTP :: Dynamic Content
Classifier: Topic :: Software Development :: Libraries :: Python Modules
Requires-Dist: requests (>=2.25.1,<3.0.0)
Requires-Dist: tenacity (>=8.2.3,<9.0.0)
Requires-Dist: warlock (>=1.3.0,<2.0.0)
Requires-Dist: zeep (>=4.0.0,<5.0.0)
Project-URL: Repository, https://github.com/ideabosque/suitetalk_connector
